yzm_file/__init__.py
yzm_file/_create_.py
yzm_file/_read_.py
yzm_file/_static_method_.py
yzm_file/_thread_file_.py
yzm_file/_util_.py
yzm_file-0.0.2.dist-info/METADATA
yzm_file-0.0.2.dist-info/WHEEL
yzm_file-0.0.2.dist-info/licenses/LICENSE
yzm_file-0.0.2.dist-info/RECORD
